sparsecca/__init__.py
sparsecca/_cca_ipls.py
sparsecca/_cca_pmd.py
sparsecca/_multicca_lp.py
sparsecca/_multicca_pmd.py
sparsecca/_multicca_pmd_permute.py
sparsecca/_pmd.py
sparsecca/_utils_pmd.py
sparsecca-0.3.1.dist-info/LICENSE
sparsecca-0.3.1.dist-info/WHEEL
sparsecca-0.3.1.dist-info/METADATA
sparsecca-0.3.1.dist-info/RECORD
