Metadata-Version: 2.1
Name: sparsecca
Version: 0.3.1
Summary: A full implementation of sparse CCA.
Author: theislab, Erkka Heinila
Maintainer-email: Yuge Ji <jiyuge@gmail.com>
Requires-Python: >=3.8
Requires-Dist: pandas
Requires-Dist: numpy
Requires-Dist: statsmodels
Requires-Dist: pyomo
Requires-Dist: bump2version ; extra == "dev"
Requires-Dist: pre-commit ; extra == "dev"
Requires-Dist: twine>=4.0.2 ; extra == "dev"
Requires-Dist: sphinx>=4 ; extra == "doc"
Requires-Dist: sphinx-book-theme>=0.3.3 ; extra == "doc"
Requires-Dist: myst-nb ; extra == "doc"
Requires-Dist: sphinxcontrib-bibtex>=1.0.0 ; extra == "doc"
Requires-Dist: sphinx-autodoc-typehints ; extra == "doc"
Requires-Dist: ipykernel ; extra == "doc"
Requires-Dist: ipython ; extra == "doc"
Requires-Dist: sphinx-copybutton ; extra == "doc"
Requires-Dist: pytest ; extra == "test"
Requires-Dist: pytest-cov ; extra == "test"
Requires-Dist: codecov ; extra == "test"
Provides-Extra: dev
Provides-Extra: doc
Provides-Extra: test
